bill_calculator_hep/AWSBillAnalysis.py
bill_calculator_hep/GCEBillAnalysis.py
bill_calculator_hep/ServiceDeskProxy.py
bill_calculator_hep/ServiceNowHandler.py
bill_calculator_hep/__init__.py
bill_calculator_hep/graphite.py
bill_calculator_hep/submitAlarm.py
bill_calculator_hep-0.2.3.dist-info/LICENSE.md
bill_calculator_hep-0.2.3.dist-info/METADATA
bill_calculator_hep-0.2.3.dist-info/WHEEL
bill_calculator_hep-0.2.3.dist-info/top_level.txt
bill_calculator_hep-0.2.3.dist-info/RECORD
