Metadata-Version: 2.1
Name: bill-calculator-hep
Version: 0.2.3
Summary: Billing calculations and threshold alarms for hybrid cloud setups
Home-page: https://github.com/HEPCloud/bill-calculator-hep
Author: Maria P. Acosta F./HEPCloud project
Author-email: macosta@fnal.gov
License: MIT
Platform: UNKNOWN
Classifier: Programming Language :: Python :: 3
Classifier: License :: OSI Approved :: MIT License
Classifier: Operating System :: OS Independent
Requires-Python: >=3.4
License-File: LICENSE.md
Requires-Dist: gcs-oauth2-boto-plugin
Requires-Dist: pyparsing
Requires-Dist: google-cloud-bigquery[pandas]
